peagen/__init__.py
peagen/_api_key.py
peagen/_banner.py
peagen/_config.py
peagen/_external.py
peagen/_gitops.py
peagen/_graph.py
peagen/_llm.py
peagen/_processing.py
peagen/_rendering.py
peagen/_source_packages.py
peagen/_template_sets.py
peagen/cli.py
peagen/cli_common.py
peagen/commands/__init__.py
peagen/commands/doe.py
peagen/commands/eval.py
peagen/commands/extras.py
peagen/commands/init.py
peagen/commands/process.py
peagen/commands/program.py
peagen/commands/revise.py
peagen/commands/sort.py
peagen/commands/templates.py
peagen/commands/validate.py
peagen/core.py
peagen/doe.py
peagen/eval/__init__.py
peagen/eval/pools/default.py
peagen/evaluator_pools/__init__.py
peagen/manifest_writer.py
peagen/plugin_registry.py
peagen/publishers/__init__.py
peagen/publishers/rabbitmq_publisher.py
peagen/publishers/redis_publisher.py
peagen/publishers/webhook_publisher.py
peagen/scaffold/ci/ci-github/.github/workflows/peagen.yml.j2
peagen/scaffold/ci/ci-gitlab/.gitlab-ci.yml.j2
peagen/scaffold/doe_spec/README.md
peagen/scaffold/doe_spec/doe_spec.yml.j2
peagen/scaffold/doe_spec/spec.yaml.j2
peagen/scaffold/project/.peagen.toml.j2
peagen/scaffold/project/LICENSE.j2
peagen/scaffold/project/README.md.j2
peagen/scaffold/project/project.yaml.j2
peagen/scaffold/template_set/agent_default.j2
peagen/scaffold/template_set/ptree.yaml.j2
peagen/scaffold/template_set/pyproject.toml.j2
peagen/scaffold/template_set/template_payload.yaml
peagen/scaffold/template_set/{{ PROJECT_ROOT }}/greeting.txt.j2
peagen/scaffold/template_set/{{ PROJECT_ROOT }}/hello.txt.j2
peagen/schemas/__init__.py
peagen/schemas/doe_spec.schema.v1.json
peagen/schemas/event.schema.v1.json
peagen/schemas/extras/component.schema.v1.json
peagen/schemas/extras/cpp_python_pkg.schema.v1.json
peagen/schemas/extras/no_requirements.schema.v1.json
peagen/schemas/extras/python_api_gw.schema.v1.json
peagen/schemas/extras/python_api_gw_service.schema.v1.json
peagen/schemas/extras/python_orm.schema.v1.json
peagen-0.1.3.dist-info/LICENSE
peagen-0.1.3.dist-info/METADATA
peagen-0.1.3.dist-info/WHEEL
peagen-0.1.3.dist-info/entry_points.txt
peagen-0.1.3.dist-info/RECORD
