Metadata-Version: 2.3
Name: peagen
Version: 0.1.3
Summary: Swarmauri's Peagan - An AI-driven contextual, dependency-based scaffolding tool for rapid content generation.
License: Apache-2.0
Author: Jacob Stewart
Author-email: jacob@swarmauri.com
Requires-Python: >=3.10,<3.13
Classifier: License :: OSI Approved :: Apache Software License
Classifier: Programming Language :: Python :: 3.10
Classifier: Programming Language :: Python :: 3.11
Classifier: Programming Language :: Python :: 3.12
Requires-Dist: PyGithub
Requires-Dist: colorama
Requires-Dist: httpx (>=0.27.0)
Requires-Dist: inflect
Requires-Dist: jinja2 (>=3.1.6)
Requires-Dist: jsonpatch (>=1.33)
Requires-Dist: minio
Requires-Dist: pika
Requires-Dist: python-dotenv
Requires-Dist: redis
Requires-Dist: swarmauri
Requires-Dist: swarmauri_base
Requires-Dist: swarmauri_core
Requires-Dist: swarmauri_prompt_j2prompttemplate
Requires-Dist: swarmauri_standard
Requires-Dist: typer
